ncatpy/__init__.py
ncatpy/api.py
ncatpy/client.py
ncatpy/faces.py
ncatpy/flags.py
ncatpy/http.py
ncatpy/logging.py
ncatpy/message.py
ncatpy/setting.py
ncatpy/status.py
ncatpy/wsapi.py
ncatpy/wstart.py
ncatpy/apis/__init__.py
ncatpy/apis/message.py
ncatpy/plugins/XunfeiGPT.py
ncatpy/plugins/__init__.py
ncatpy-1.0.0.dist-info/LICENSE
ncatpy-1.0.0.dist-info/METADATA
ncatpy-1.0.0.dist-info/WHEEL
ncatpy-1.0.0.dist-info/top_level.txt
ncatpy-1.0.0.dist-info/RECORD
