Metadata-Version: 2.1
Name: ncatpy
Version: 1.0.0
Summary: 基于Napcat.QQ开发的pythonsdk
Home-page: https://github.com/liyihao1110/NcatBot
Author: 木子
Author-email: 2793415370@qq.com
Classifier: Programming Language :: Python :: 3
Classifier: License :: OSI Approved :: MIT License
Classifier: Operating System :: OS Independent
Requires-Python: >=3.10
License-File: LICENSE
Requires-Dist: websockets
Requires-Dist: requests
Requires-Dist: aiohttp
Requires-Dist: PyYAML
Requires-Dist: httpx
